setup.py
distributions12/Binomialdistribution.py
distributions12/Gaussiandistribution.py
distributions12/Generaldistribution.py
distributions12/__init__.py
distributions12.egg-info/PKG-INFO
distributions12.egg-info/SOURCES.txt
distributions12.egg-info/dependency_links.txt
distributions12.egg-info/not-zip-safe
distributions12.egg-info/top_level.txt