Metadata-Version: 1.0
Name: distributions12
Version: 0.1
Summary: Gaussian and Bionomial distributions
Home-page: UNKNOWN
Author: abc
Author-email: UNKNOWN
License: UNKNOWN
Platform: UNKNOWN
